cyfi/__init__.py
cyfi/__main__.py
cyfi/cli.py
cyfi/config.py
cyfi/evaluate.py
cyfi/experiment.py
cyfi/pipeline.py
cyfi/version.py
cyfi/visualize.py
cyfi/assets/model_v0.zip
cyfi/data/features.py
cyfi/data/satellite_data.py
cyfi/data/utils.py
cyfi-1.1.5.dist-info/entry_points.txt
cyfi-1.1.5.dist-info/licenses/LICENSE
cyfi-1.1.5.dist-info/WHEEL
cyfi-1.1.5.dist-info/METADATA
cyfi-1.1.5.dist-info/RECORD
