Metadata-Version: 2.4
Name: cyfi
Version: 1.1.5
Summary: Estimate cyanobacteria density in small, inland water bodies using Sentinel-2 satellite imagery.
Keywords: cyanobacteria,harmful algal blooms,HABs,sentinel-2,satellite imagery
Author-email: DrivenData <info@drivendata.org>
Requires-Python: >=3.10
Classifier: Programming Language :: Python :: 3
Classifier: Programming Language :: Python :: 3.10
Classifier: Programming Language :: Python :: 3.11
Classifier: License :: OSI Approved :: MIT License
Classifier: Operating System :: OS Independent
License-File: LICENSE
Requires-Dist: cloudpathlib[s3]>=0.4.1
Requires-Dist: geopandas
Requires-Dist: geopy
Requires-Dist: GitPython
Requires-Dist: gradio>=5.0
Requires-Dist: lightgbm
Requires-Dist: loguru
Requires-Dist: matplotlib
Requires-Dist: numpy
Requires-Dist: odc-stac
Requires-Dist: opencv-python
Requires-Dist: pandas
Requires-Dist: planetary-computer
Requires-Dist: platformdirs
Requires-Dist: plotly
Requires-Dist: pydantic>=2.0
Requires-Dist: pystac
Requires-Dist: pystac-client
Requires-Dist: scikit-learn>=1.4
Requires-Dist: seaborn
Requires-Dist: repro-zipfile
Requires-Dist: rioxarray
Requires-Dist: tqdm
Requires-Dist: typer>=0.16.0
Requires-Dist: xarray[accel, io, parallel]
Requires-Dist: build ; extra == "dev"
Requires-Dist: black ; extra == "dev"
Requires-Dist: flake8 ; extra == "dev"
Requires-Dist: jupyter ; extra == "dev"
Requires-Dist: mkdocs ; extra == "dev"
Requires-Dist: mkdocs-bootswatch ; extra == "dev"
Requires-Dist: pytest ; extra == "dev"
Requires-Dist: pytest-cov ; extra == "dev"
Requires-Dist: pytest_mock ; extra == "dev"
Project-URL: Bug Tracker, https://github.com/drivendataorg/cyfi/issues
Project-URL: Changelog, https://cyfi.drivendata.org/changelog/
Project-URL: Documentation, https://cyfi.drivendata.org/
Project-URL: Repository, https://github.com/drivendataorg/cyfi
Provides-Extra: dev
